{
  "children": [
    {
      "name": "Säugetiere",
      "children": [
        {
          "name": "Nicht gefährdet",
          "value": 65,
          "colorsam": "springgreen3"
        },
        {
          "name": "Mensch",
          "value": 1,
          "colorsam": "yellow"
        },
        {
          "name": "Gefährdet",
          "group": "B",
          "value": 16,
          "colorsam": "red3"
        },
        {
          "name": "Stark gefährdet",
          "group": "A",
          "value": 12,
          "colorsam": "red2"
        },
        {
          "name": "Vom Aussterben bedroht",
          "group": "A",
          "value": 5,
          "colorsam": "red1"
        }
      ]
    },
    {
      "name": "Vögel",
      "children": [
        {
          "name": "Nicht gefährdet",
          "value": 129,
          "colorsam": "springgreen3"
        },
        {
          "name": "Gefährdet",
          "group": "C",
          "value": 42,
          "colorsam": "red3"
        },
        {
          "name": "Stark gefährdet",
          "group": "C",
          "value": 25,
          "colorsam": "red2"
        },
        {
          "name": "Vom Aussterben bedroht",
          "group": "C",
          "value": 9,
          "colorsam": "red1"
        }
      ]
    },
    {
      "name": "Amphibien",
      "children": [
        {
          "name": "Nicht gefährdet",
          "value": 5,
          "colorsam": "springgreen3"
        },
        {
          "name": "Gefährdet",
          "group": "C",
          "value": 8,
          "colorsam": "red3"
        },
        {
          "name": "Stark gefährdet",
          "group": "C",
          "value": 6,
          "colorsam": "red2"
        }
      ]
    },
    {
      "name": "Reptilien",
      "children": [
        {
          "name": "Nicht gefährdet",
          "value": 6,
          "colorsam": "springgreen3"
        },
        {
          "name": "Gefährdet",
          "group": "C",
          "value": 2,
          "colorsam": "red3"
        },
        {
          "name": "Stark gefährdet",
          "group": "C",
          "value": 9,
          "colorsam": "red2"
        },
        {
          "name": "Vom Aussterben bedroht",
          "group": "C",
          "value": 2,
          "colorsam": "red1"
        }
      ]
    },
    {
      "name": "Fische",
      "children": [
        {
          "name": "Nicht gefährdet",
          "value": 56,
          "colorsam": "springgreen3"
        },
        {
          "name": "Gefährdet",
          "group": "C",
          "value": 11,
          "colorsam": "red3"
        },
        {
          "name": "Stark gefährdet",
          "group": "C",
          "value": 8,
          "colorsam": "red2"
        },
        {
          "name": "Vom Aussterben bedroht",
          "group": "C",
          "value": 15,
          "colorsam": "red1"
        }
      ]
    }
  ]
}